{"nodes": [{"id": "android_app_src_main_kotlin_com_paul_sprintsync_feature_motion_data_native_sensornativecontroller_kt", "label": "SensorNativeController.kt", "file_type": "code", "source_file": "android\\app\\src\\main\\kotlin\\com\\paul\\sprintsync\\feature\\motion\\data\\native\\SensorNativeController.kt", "source_location": "L1"}, {"id": "sensornativecontroller_sensornativecontroller", "label": "SensorNativeController", "file_type": "code", "source_file": "android\\app\\src\\main\\kotlin\\com\\paul\\sprintsync\\feature\\motion\\data\\native\\SensorNativeController.kt", "source_location": "L23"}, {"id": "sensornativecontroller_onlocationchanged", "label": "onLocationChanged()", "file_type": "code", "source_file": "android\\app\\src\\main\\kotlin\\com\\paul\\sprintsync\\feature\\motion\\data\\native\\SensorNativeController.kt", "source_location": "L105"}, {"id": "sensornativecontroller_onproviderdisabled", "label": "onProviderDisabled()", "file_type": "code", "source_file": "android\\app\\src\\main\\kotlin\\com\\paul\\sprintsync\\feature\\motion\\data\\native\\SensorNativeController.kt", "source_location": "L113"}, {"id": "sensornativecontroller_onproviderenabled", "label": "onProviderEnabled()", "file_type": "code", "source_file": "android\\app\\src\\main\\kotlin\\com\\paul\\sprintsync\\feature\\motion\\data\\native\\SensorNativeController.kt", "source_location": "L119"}, {"id": "sensornativecontroller_onstatuschanged", "label": "onStatusChanged()", "file_type": "code", "source_file": "android\\app\\src\\main\\kotlin\\com\\paul\\sprintsync\\feature\\motion\\data\\native\\SensorNativeController.kt", "source_location": "L123"}, {"id": "sensornativecontroller_sensornativecontroller_seteventlistener", "label": ".setEventListener()", "file_type": "code", "source_file": "android\\app\\src\\main\\kotlin\\com\\paul\\sprintsync\\feature\\motion\\data\\native\\SensorNativeController.kt", "source_location": "L129"}, {"id": "sensornativecontroller_sensornativecontroller_onhostpaused", "label": ".onHostPaused()", "file_type": "code", "source_file": "android\\app\\src\\main\\kotlin\\com\\paul\\sprintsync\\feature\\motion\\data\\native\\SensorNativeController.kt", "source_location": "L133"}, {"id": "sensornativecontroller_sensornativecontroller_onhostresumed", "label": ".onHostResumed()", "file_type": "code", "source_file": "android\\app\\src\\main\\kotlin\\com\\paul\\sprintsync\\feature\\motion\\data\\native\\SensorNativeController.kt", "source_location": "L140"}, {"id": "sensornativecontroller_sensornativecontroller_dispose", "label": ".dispose()", "file_type": "code", "source_file": "android\\app\\src\\main\\kotlin\\com\\paul\\sprintsync\\feature\\motion\\data\\native\\SensorNativeController.kt", "source_location": "L158"}, {"id": "sensornativecontroller_sensornativecontroller_attachpreviewsurface", "label": ".attachPreviewSurface()", "file_type": "code", "source_file": "android\\app\\src\\main\\kotlin\\com\\paul\\sprintsync\\feature\\motion\\data\\native\\SensorNativeController.kt", "source_location": "L165"}, {"id": "sensornativecontroller_sensornativecontroller_detachpreviewsurface", "label": ".detachPreviewSurface()", "file_type": "code", "source_file": "android\\app\\src\\main\\kotlin\\com\\paul\\sprintsync\\feature\\motion\\data\\native\\SensorNativeController.kt", "source_location": "L176"}, {"id": "sensornativecontroller_sensornativecontroller_currentclocksyncelapsednanos", "label": ".currentClockSyncElapsedNanos()", "file_type": "code", "source_file": "android\\app\\src\\main\\kotlin\\com\\paul\\sprintsync\\feature\\motion\\data\\native\\SensorNativeController.kt", "source_location": "L190"}, {"id": "sensornativecontroller_sensornativecontroller_startnativemonitoring", "label": ".startNativeMonitoring()", "file_type": "code", "source_file": "android\\app\\src\\main\\kotlin\\com\\paul\\sprintsync\\feature\\motion\\data\\native\\SensorNativeController.kt", "source_location": "L206"}, {"id": "sensornativecontroller_sensornativecontroller_warmupgpssync", "label": ".warmupGpsSync()", "file_type": "code", "source_file": "android\\app\\src\\main\\kotlin\\com\\paul\\sprintsync\\feature\\motion\\data\\native\\SensorNativeController.kt", "source_location": "L238"}, {"id": "sensornativecontroller_sensornativecontroller_stopnativemonitoring", "label": ".stopNativeMonitoring()", "file_type": "code", "source_file": "android\\app\\src\\main\\kotlin\\com\\paul\\sprintsync\\feature\\motion\\data\\native\\SensorNativeController.kt", "source_location": "L242"}, {"id": "sensornativecontroller_sensornativecontroller_updatenativeconfig", "label": ".updateNativeConfig()", "file_type": "code", "source_file": "android\\app\\src\\main\\kotlin\\com\\paul\\sprintsync\\feature\\motion\\data\\native\\SensorNativeController.kt", "source_location": "L246"}, {"id": "sensornativecontroller_sensornativecontroller_resetnativerun", "label": ".resetNativeRun()", "file_type": "code", "source_file": "android\\app\\src\\main\\kotlin\\com\\paul\\sprintsync\\feature\\motion\\data\\native\\SensorNativeController.kt", "source_location": "L257"}, {"id": "sensornativecontroller_sensornativecontroller_analyze", "label": ".analyze()", "file_type": "code", "source_file": "android\\app\\src\\main\\kotlin\\com\\paul\\sprintsync\\feature\\motion\\data\\native\\SensorNativeController.kt", "source_location": "L261"}, {"id": "sensornativecontroller_sensornativecontroller_startmonitoringbackend", "label": ".startMonitoringBackend()", "file_type": "code", "source_file": "android\\app\\src\\main\\kotlin\\com\\paul\\sprintsync\\feature\\motion\\data\\native\\SensorNativeController.kt", "source_location": "L306"}, {"id": "sensornativecontroller_sensornativecontroller_startnormalbackend", "label": ".startNormalBackend()", "file_type": "code", "source_file": "android\\app\\src\\main\\kotlin\\com\\paul\\sprintsync\\feature\\motion\\data\\native\\SensorNativeController.kt", "source_location": "L310"}, {"id": "sensornativecontroller_sensornativecontroller_stopnativemonitoringinternal", "label": ".stopNativeMonitoringInternal()", "file_type": "code", "source_file": "android\\app\\src\\main\\kotlin\\com\\paul\\sprintsync\\feature\\motion\\data\\native\\SensorNativeController.kt", "source_location": "L339"}, {"id": "sensornativecontroller_sensornativecontroller_restartmonitoringbackend", "label": ".restartMonitoringBackend()", "file_type": "code", "source_file": "android\\app\\src\\main\\kotlin\\com\\paul\\sprintsync\\feature\\motion\\data\\native\\SensorNativeController.kt", "source_location": "L352"}, {"id": "sensornativecontroller_sensornativecontroller_resetnativeruninternal", "label": ".resetNativeRunInternal()", "file_type": "code", "source_file": "android\\app\\src\\main\\kotlin\\com\\paul\\sprintsync\\feature\\motion\\data\\native\\SensorNativeController.kt", "source_location": "L374"}, {"id": "sensornativecontroller_sensornativecontroller_resetstreamstate", "label": ".resetStreamState()", "file_type": "code", "source_file": "android\\app\\src\\main\\kotlin\\com\\paul\\sprintsync\\feature\\motion\\data\\native\\SensorNativeController.kt", "source_location": "L382"}, {"id": "sensornativecontroller_sensornativecontroller_rebindcamerausecasesifmonitoring", "label": ".rebindCameraUseCasesIfMonitoring()", "file_type": "code", "source_file": "android\\app\\src\\main\\kotlin\\com\\paul\\sprintsync\\feature\\motion\\data\\native\\SensorNativeController.kt", "source_location": "L400"}, {"id": "sensornativecontroller_sensornativecontroller_attemptpreviewrebind", "label": ".attemptPreviewRebind()", "file_type": "code", "source_file": "android\\app\\src\\main\\kotlin\\com\\paul\\sprintsync\\feature\\motion\\data\\native\\SensorNativeController.kt", "source_location": "L409"}, {"id": "sensornativecontroller_sensornativecontroller_schedulepreviewrebindretriesifmonitoring", "label": ".schedulePreviewRebindRetriesIfMonitoring()", "file_type": "code", "source_file": "android\\app\\src\\main\\kotlin\\com\\paul\\sprintsync\\feature\\motion\\data\\native\\SensorNativeController.kt", "source_location": "L426"}, {"id": "sensornativecontroller_sensornativecontroller_cancelpreviewrebindretries", "label": ".cancelPreviewRebindRetries()", "file_type": "code", "source_file": "android\\app\\src\\main\\kotlin\\com\\paul\\sprintsync\\feature\\motion\\data\\native\\SensorNativeController.kt", "source_location": "L469"}, {"id": "sensornativecontroller_sensornativecontroller_scheduleanalyzerinactivitywatchdog", "label": ".scheduleAnalyzerInactivityWatchdog()", "file_type": "code", "source_file": "android\\app\\src\\main\\kotlin\\com\\paul\\sprintsync\\feature\\motion\\data\\native\\SensorNativeController.kt", "source_location": "L475"}, {"id": "sensornativecontroller_sensornativecontroller_cancelanalyzerinactivitywatchdog", "label": ".cancelAnalyzerInactivityWatchdog()", "file_type": "code", "source_file": "android\\app\\src\\main\\kotlin\\com\\paul\\sprintsync\\feature\\motion\\data\\native\\SensorNativeController.kt", "source_location": "L502"}, {"id": "sensornativecontroller_sensornativecontroller_logruntimediagnostic", "label": ".logRuntimeDiagnostic()", "file_type": "code", "source_file": "android\\app\\src\\main\\kotlin\\com\\paul\\sprintsync\\feature\\motion\\data\\native\\SensorNativeController.kt", "source_location": "L507"}, {"id": "sensornativecontroller_sensornativecontroller_updatestreamtelemetry", "label": ".updateStreamTelemetry()", "file_type": "code", "source_file": "android\\app\\src\\main\\kotlin\\com\\paul\\sprintsync\\feature\\motion\\data\\native\\SensorNativeController.kt", "source_location": "L511"}, {"id": "sensornativecontroller_sensornativecontroller_startgpsupdatesifavailable", "label": ".startGpsUpdatesIfAvailable()", "file_type": "code", "source_file": "android\\app\\src\\main\\kotlin\\com\\paul\\sprintsync\\feature\\motion\\data\\native\\SensorNativeController.kt", "source_location": "L526"}, {"id": "sensornativecontroller_sensornativecontroller_stopgpsupdates", "label": ".stopGpsUpdates()", "file_type": "code", "source_file": "android\\app\\src\\main\\kotlin\\com\\paul\\sprintsync\\feature\\motion\\data\\native\\SensorNativeController.kt", "source_location": "L558"}, {"id": "sensornativecontroller_sensornativecontroller_emitframestats", "label": ".emitFrameStats()", "file_type": "code", "source_file": "android\\app\\src\\main\\kotlin\\com\\paul\\sprintsync\\feature\\motion\\data\\native\\SensorNativeController.kt", "source_location": "L570"}, {"id": "sensornativecontroller_sensornativecontroller_emittrigger", "label": ".emitTrigger()", "file_type": "code", "source_file": "android\\app\\src\\main\\kotlin\\com\\paul\\sprintsync\\feature\\motion\\data\\native\\SensorNativeController.kt", "source_location": "L593"}, {"id": "sensornativecontroller_sensornativecontroller_emitstate", "label": ".emitState()", "file_type": "code", "source_file": "android\\app\\src\\main\\kotlin\\com\\paul\\sprintsync\\feature\\motion\\data\\native\\SensorNativeController.kt", "source_location": "L597"}, {"id": "sensornativecontroller_sensornativecontroller_emitdiagnostic", "label": ".emitDiagnostic()", "file_type": "code", "source_file": "android\\app\\src\\main\\kotlin\\com\\paul\\sprintsync\\feature\\motion\\data\\native\\SensorNativeController.kt", "source_location": "L609"}, {"id": "sensornativecontroller_sensornativecontroller_emiterror", "label": ".emitError()", "file_type": "code", "source_file": "android\\app\\src\\main\\kotlin\\com\\paul\\sprintsync\\feature\\motion\\data\\native\\SensorNativeController.kt", "source_location": "L613"}, {"id": "sensornativecontroller_sensornativecontroller_emitevent", "label": ".emitEvent()", "file_type": "code", "source_file": "android\\app\\src\\main\\kotlin\\com\\paul\\sprintsync\\feature\\motion\\data\\native\\SensorNativeController.kt", "source_location": "L617"}, {"id": "sensornativecontroller_shouldschedulepreviewrebindretry", "label": "shouldSchedulePreviewRebindRetry()", "file_type": "code", "source_file": "android\\app\\src\\main\\kotlin\\com\\paul\\sprintsync\\feature\\motion\\data\\native\\SensorNativeController.kt", "source_location": "L623"}], "edges": [{"source": "android_app_src_main_kotlin_com_paul_sprintsync_feature_motion_data_native_sensornativecontroller_kt", "target": "sensornativecontroller_sensornativecontroller", "relation": "contains", "confidence": "EXTRACTED", "source_file": "android\\app\\src\\main\\kotlin\\com\\paul\\sprintsync\\feature\\motion\\data\\native\\SensorNativeController.kt", "source_location": "L23", "weight": 1.0}, {"source": "android_app_src_main_kotlin_com_paul_sprintsync_feature_motion_data_native_sensornativecontroller_kt", "target": "sensornativecontroller_onlocationchanged", "relation": "contains", "confidence": "EXTRACTED", "source_file": "android\\app\\src\\main\\kotlin\\com\\paul\\sprintsync\\feature\\motion\\data\\native\\SensorNativeController.kt", "source_location": "L105", "weight": 1.0}, {"source": "android_app_src_main_kotlin_com_paul_sprintsync_feature_motion_data_native_sensornativecontroller_kt", "target": "sensornativecontroller_onproviderdisabled", "relation": "contains", "confidence": "EXTRACTED", "source_file": "android\\app\\src\\main\\kotlin\\com\\paul\\sprintsync\\feature\\motion\\data\\native\\SensorNativeController.kt", "source_location": "L113", "weight": 1.0}, {"source": "android_app_src_main_kotlin_com_paul_sprintsync_feature_motion_data_native_sensornativecontroller_kt", "target": "sensornativecontroller_onproviderenabled", "relation": "contains", "confidence": "EXTRACTED", "source_file": "android\\app\\src\\main\\kotlin\\com\\paul\\sprintsync\\feature\\motion\\data\\native\\SensorNativeController.kt", "source_location": "L119", "weight": 1.0}, {"source": "android_app_src_main_kotlin_com_paul_sprintsync_feature_motion_data_native_sensornativecontroller_kt", "target": "sensornativecontroller_onstatuschanged", "relation": "contains", "confidence": "EXTRACTED", "source_file": "android\\app\\src\\main\\kotlin\\com\\paul\\sprintsync\\feature\\motion\\data\\native\\SensorNativeController.kt", "source_location": "L123", "weight": 1.0}, {"source": "sensornativecontroller_sensornativecontroller", "target": "sensornativecontroller_sensornativecontroller_seteventlistener", "relation": "method", "confidence": "EXTRACTED", "source_file": "android\\app\\src\\main\\kotlin\\com\\paul\\sprintsync\\feature\\motion\\data\\native\\SensorNativeController.kt", "source_location": "L129", "weight": 1.0}, {"source": "sensornativecontroller_sensornativecontroller", "target": "sensornativecontroller_sensornativecontroller_onhostpaused", "relation": "method", "confidence": "EXTRACTED", "source_file": "android\\app\\src\\main\\kotlin\\com\\paul\\sprintsync\\feature\\motion\\data\\native\\SensorNativeController.kt", "source_location": "L133", "weight": 1.0}, {"source": "sensornativecontroller_sensornativecontroller", "target": "sensornativecontroller_sensornativecontroller_onhostresumed", "relation": "method", "confidence": "EXTRACTED", "source_file": "android\\app\\src\\main\\kotlin\\com\\paul\\sprintsync\\feature\\motion\\data\\native\\SensorNativeController.kt", "source_location": "L140", "weight": 1.0}, {"source": "sensornativecontroller_sensornativecontroller", "target": "sensornativecontroller_sensornativecontroller_dispose", "relation": "method", "confidence": "EXTRACTED", "source_file": "android\\app\\src\\main\\kotlin\\com\\paul\\sprintsync\\feature\\motion\\data\\native\\SensorNativeController.kt", "source_location": "L158", "weight": 1.0}, {"source": "sensornativecontroller_sensornativecontroller", "target": "sensornativecontroller_sensornativecontroller_attachpreviewsurface", "relation": "method", "confidence": "EXTRACTED", "source_file": "android\\app\\src\\main\\kotlin\\com\\paul\\sprintsync\\feature\\motion\\data\\native\\SensorNativeController.kt", "source_location": "L165", "weight": 1.0}, {"source": "sensornativecontroller_sensornativecontroller", "target": "sensornativecontroller_sensornativecontroller_detachpreviewsurface", "relation": "method", "confidence": "EXTRACTED", "source_file": "android\\app\\src\\main\\kotlin\\com\\paul\\sprintsync\\feature\\motion\\data\\native\\SensorNativeController.kt", "source_location": "L176", "weight": 1.0}, {"source": "sensornativecontroller_sensornativecontroller", "target": "sensornativecontroller_sensornativecontroller_currentclocksyncelapsednanos", "relation": "method", "confidence": "EXTRACTED", "source_file": "android\\app\\src\\main\\kotlin\\com\\paul\\sprintsync\\feature\\motion\\data\\native\\SensorNativeController.kt", "source_location": "L190", "weight": 1.0}, {"source": "sensornativecontroller_sensornativecontroller", "target": "sensornativecontroller_sensornativecontroller_startnativemonitoring", "relation": "method", "confidence": "EXTRACTED", "source_file": "android\\app\\src\\main\\kotlin\\com\\paul\\sprintsync\\feature\\motion\\data\\native\\SensorNativeController.kt", "source_location": "L206", "weight": 1.0}, {"source": "sensornativecontroller_sensornativecontroller", "target": "sensornativecontroller_sensornativecontroller_warmupgpssync", "relation": "method", "confidence": "EXTRACTED", "source_file": "android\\app\\src\\main\\kotlin\\com\\paul\\sprintsync\\feature\\motion\\data\\native\\SensorNativeController.kt", "source_location": "L238", "weight": 1.0}, {"source": "sensornativecontroller_sensornativecontroller", "target": "sensornativecontroller_sensornativecontroller_stopnativemonitoring", "relation": "method", "confidence": "EXTRACTED", "source_file": "android\\app\\src\\main\\kotlin\\com\\paul\\sprintsync\\feature\\motion\\data\\native\\SensorNativeController.kt", "source_location": "L242", "weight": 1.0}, {"source": "sensornativecontroller_sensornativecontroller", "target": "sensornativecontroller_sensornativecontroller_updatenativeconfig", "relation": "method", "confidence": "EXTRACTED", "source_file": "android\\app\\src\\main\\kotlin\\com\\paul\\sprintsync\\feature\\motion\\data\\native\\SensorNativeController.kt", "source_location": "L246", "weight": 1.0}, {"source": "sensornativecontroller_sensornativecontroller", "target": "sensornativecontroller_sensornativecontroller_resetnativerun", "relation": "method", "confidence": "EXTRACTED", "source_file": "android\\app\\src\\main\\kotlin\\com\\paul\\sprintsync\\feature\\motion\\data\\native\\SensorNativeController.kt", "source_location": "L257", "weight": 1.0}, {"source": "sensornativecontroller_sensornativecontroller", "target": "sensornativecontroller_sensornativecontroller_analyze", "relation": "method", "confidence": "EXTRACTED", "source_file": "android\\app\\src\\main\\kotlin\\com\\paul\\sprintsync\\feature\\motion\\data\\native\\SensorNativeController.kt", "source_location": "L261", "weight": 1.0}, {"source": "sensornativecontroller_sensornativecontroller", "target": "sensornativecontroller_sensornativecontroller_startmonitoringbackend", "relation": "method", "confidence": "EXTRACTED", "source_file": "android\\app\\src\\main\\kotlin\\com\\paul\\sprintsync\\feature\\motion\\data\\native\\SensorNativeController.kt", "source_location": "L306", "weight": 1.0}, {"source": "sensornativecontroller_sensornativecontroller", "target": "sensornativecontroller_sensornativecontroller_startnormalbackend", "relation": "method", "confidence": "EXTRACTED", "source_file": "android\\app\\src\\main\\kotlin\\com\\paul\\sprintsync\\feature\\motion\\data\\native\\SensorNativeController.kt", "source_location": "L310", "weight": 1.0}, {"source": "sensornativecontroller_sensornativecontroller", "target": "sensornativecontroller_sensornativecontroller_stopnativemonitoringinternal", "relation": "method", "confidence": "EXTRACTED", "source_file": "android\\app\\src\\main\\kotlin\\com\\paul\\sprintsync\\feature\\motion\\data\\native\\SensorNativeController.kt", "source_location": "L339", "weight": 1.0}, {"source": "sensornativecontroller_sensornativecontroller", "target": "sensornativecontroller_sensornativecontroller_restartmonitoringbackend", "relation": "method", "confidence": "EXTRACTED", "source_file": "android\\app\\src\\main\\kotlin\\com\\paul\\sprintsync\\feature\\motion\\data\\native\\SensorNativeController.kt", "source_location": "L352", "weight": 1.0}, {"source": "sensornativecontroller_sensornativecontroller", "target": "sensornativecontroller_sensornativecontroller_resetnativeruninternal", "relation": "method", "confidence": "EXTRACTED", "source_file": "android\\app\\src\\main\\kotlin\\com\\paul\\sprintsync\\feature\\motion\\data\\native\\SensorNativeController.kt", "source_location": "L374", "weight": 1.0}, {"source": "sensornativecontroller_sensornativecontroller", "target": "sensornativecontroller_sensornativecontroller_resetstreamstate", "relation": "method", "confidence": "EXTRACTED", "source_file": "android\\app\\src\\main\\kotlin\\com\\paul\\sprintsync\\feature\\motion\\data\\native\\SensorNativeController.kt", "source_location": "L382", "weight": 1.0}, {"source": "sensornativecontroller_sensornativecontroller", "target": "sensornativecontroller_sensornativecontroller_rebindcamerausecasesifmonitoring", "relation": "method", "confidence": "EXTRACTED", "source_file": "android\\app\\src\\main\\kotlin\\com\\paul\\sprintsync\\feature\\motion\\data\\native\\SensorNativeController.kt", "source_location": "L400", "weight": 1.0}, {"source": "sensornativecontroller_sensornativecontroller", "target": "sensornativecontroller_sensornativecontroller_attemptpreviewrebind", "relation": "method", "confidence": "EXTRACTED", "source_file": "android\\app\\src\\main\\kotlin\\com\\paul\\sprintsync\\feature\\motion\\data\\native\\SensorNativeController.kt", "source_location": "L409", "weight": 1.0}, {"source": "sensornativecontroller_sensornativecontroller", "target": "sensornativecontroller_sensornativecontroller_schedulepreviewrebindretriesifmonitoring", "relation": "method", "confidence": "EXTRACTED", "source_file": "android\\app\\src\\main\\kotlin\\com\\paul\\sprintsync\\feature\\motion\\data\\native\\SensorNativeController.kt", "source_location": "L426", "weight": 1.0}, {"source": "sensornativecontroller_sensornativecontroller", "target": "sensornativecontroller_sensornativecontroller_cancelpreviewrebindretries", "relation": "method", "confidence": "EXTRACTED", "source_file": "android\\app\\src\\main\\kotlin\\com\\paul\\sprintsync\\feature\\motion\\data\\native\\SensorNativeController.kt", "source_location": "L469", "weight": 1.0}, {"source": "sensornativecontroller_sensornativecontroller", "target": "sensornativecontroller_sensornativecontroller_scheduleanalyzerinactivitywatchdog", "relation": "method", "confidence": "EXTRACTED", "source_file": "android\\app\\src\\main\\kotlin\\com\\paul\\sprintsync\\feature\\motion\\data\\native\\SensorNativeController.kt", "source_location": "L475", "weight": 1.0}, {"source": "sensornativecontroller_sensornativecontroller", "target": "sensornativecontroller_sensornativecontroller_cancelanalyzerinactivitywatchdog", "relation": "method", "confidence": "EXTRACTED", "source_file": "android\\app\\src\\main\\kotlin\\com\\paul\\sprintsync\\feature\\motion\\data\\native\\SensorNativeController.kt", "source_location": "L502", "weight": 1.0}, {"source": "sensornativecontroller_sensornativecontroller", "target": "sensornativecontroller_sensornativecontroller_logruntimediagnostic", "relation": "method", "confidence": "EXTRACTED", "source_file": "android\\app\\src\\main\\kotlin\\com\\paul\\sprintsync\\feature\\motion\\data\\native\\SensorNativeController.kt", "source_location": "L507", "weight": 1.0}, {"source": "sensornativecontroller_sensornativecontroller", "target": "sensornativecontroller_sensornativecontroller_updatestreamtelemetry", "relation": "method", "confidence": "EXTRACTED", "source_file": "android\\app\\src\\main\\kotlin\\com\\paul\\sprintsync\\feature\\motion\\data\\native\\SensorNativeController.kt", "source_location": "L511", "weight": 1.0}, {"source": "sensornativecontroller_sensornativecontroller", "target": "sensornativecontroller_sensornativecontroller_startgpsupdatesifavailable", "relation": "method", "confidence": "EXTRACTED", "source_file": "android\\app\\src\\main\\kotlin\\com\\paul\\sprintsync\\feature\\motion\\data\\native\\SensorNativeController.kt", "source_location": "L526", "weight": 1.0}, {"source": "sensornativecontroller_sensornativecontroller", "target": "sensornativecontroller_sensornativecontroller_stopgpsupdates", "relation": "method", "confidence": "EXTRACTED", "source_file": "android\\app\\src\\main\\kotlin\\com\\paul\\sprintsync\\feature\\motion\\data\\native\\SensorNativeController.kt", "source_location": "L558", "weight": 1.0}, {"source": "sensornativecontroller_sensornativecontroller", "target": "sensornativecontroller_sensornativecontroller_emitframestats", "relation": "method", "confidence": "EXTRACTED", "source_file": "android\\app\\src\\main\\kotlin\\com\\paul\\sprintsync\\feature\\motion\\data\\native\\SensorNativeController.kt", "source_location": "L570", "weight": 1.0}, {"source": "sensornativecontroller_sensornativecontroller", "target": "sensornativecontroller_sensornativecontroller_emittrigger", "relation": "method", "confidence": "EXTRACTED", "source_file": "android\\app\\src\\main\\kotlin\\com\\paul\\sprintsync\\feature\\motion\\data\\native\\SensorNativeController.kt", "source_location": "L593", "weight": 1.0}, {"source": "sensornativecontroller_sensornativecontroller", "target": "sensornativecontroller_sensornativecontroller_emitstate", "relation": "method", "confidence": "EXTRACTED", "source_file": "android\\app\\src\\main\\kotlin\\com\\paul\\sprintsync\\feature\\motion\\data\\native\\SensorNativeController.kt", "source_location": "L597", "weight": 1.0}, {"source": "sensornativecontroller_sensornativecontroller", "target": "sensornativecontroller_sensornativecontroller_emitdiagnostic", "relation": "method", "confidence": "EXTRACTED", "source_file": "android\\app\\src\\main\\kotlin\\com\\paul\\sprintsync\\feature\\motion\\data\\native\\SensorNativeController.kt", "source_location": "L609", "weight": 1.0}, {"source": "sensornativecontroller_sensornativecontroller", "target": "sensornativecontroller_sensornativecontroller_emiterror", "relation": "method", "confidence": "EXTRACTED", "source_file": "android\\app\\src\\main\\kotlin\\com\\paul\\sprintsync\\feature\\motion\\data\\native\\SensorNativeController.kt", "source_location": "L613", "weight": 1.0}, {"source": "sensornativecontroller_sensornativecontroller", "target": "sensornativecontroller_sensornativecontroller_emitevent", "relation": "method", "confidence": "EXTRACTED", "source_file": "android\\app\\src\\main\\kotlin\\com\\paul\\sprintsync\\feature\\motion\\data\\native\\SensorNativeController.kt", "source_location": "L617", "weight": 1.0}, {"source": "android_app_src_main_kotlin_com_paul_sprintsync_feature_motion_data_native_sensornativecontroller_kt", "target": "sensornativecontroller_shouldschedulepreviewrebindretry", "relation": "contains", "confidence": "EXTRACTED", "source_file": "android\\app\\src\\main\\kotlin\\com\\paul\\sprintsync\\feature\\motion\\data\\native\\SensorNativeController.kt", "source_location": "L623", "weight": 1.0}], "raw_calls": []}